focal/__init__.py
focal/extension_store.py
focal/parse_format.py
focal/tests/__init__.py
focal/tests/test_extension_store.py
focal-0.1.8.dist-info/LICENSE
focal-0.1.8.dist-info/METADATA
focal-0.1.8.dist-info/WHEEL
focal-0.1.8.dist-info/top_level.txt
focal-0.1.8.dist-info/RECORD
