Metadata-Version: 2.1
Name: focal
Version: 0.1.8
Summary: Data Access Objects for local files
Home-page: https://github.com/i2mint/focal
License: mit
Keywords: data access,file system,data preparation,storage,orm
Platform: any
License-File: LICENSE
Requires-Dist: dol
Requires-Dist: py2store
Requires-Dist: openpyxl
